pyquarium/__init__.py
pyquarium/__main__.py
pyquarium/aquarium.py
pyquarium-2.0.0.dist-info/licenses/LICENSE
pyquarium-2.0.0.dist-info/METADATA
pyquarium-2.0.0.dist-info/WHEEL
pyquarium-2.0.0.dist-info/top_level.txt
pyquarium-2.0.0.dist-info/RECORD
