Metadata-Version: 2.4
Name: pyquarium
Version: 2.0.0
Summary: ascii art aquarium for your terminal
Author: Alexander Walters
License: Attribution-NonCommercial-ShareAlike 4.0 International
Project-URL: Repository, https://github.com/awinstonw/pyquarium/
Requires-Python: >=3.14
License-File: LICENSE
Requires-Dist: windows-curses; sys_platform == "win32"
Dynamic: license-file
